{
	"Champion"        : "Lee Sin",
	"Role"            : "Jungle",

	"Skin"            : "Dragon Fist",
	"Chroma"          : "Emerald",

	"Creator"         : "JDog",
	"Patch"           : "v9.16",

	"Summoner Spells" : [
		"Smite",
		"Flash"
	],

	"Runes"           : {
		"Paths"         : [
			"Domination",
			"Precision"
		],
		"Primary"       : [
			"Electrocute",
			"Sudden Impact",
			"Eyeball Collection",
			"Relentless Hunter"
		],
		"Secondary"     : [
			"Triumph",
			"Legend: Tenacity"
		],
		"Shards"        : [
			"Attack Speed",
			"Adaptive Force",
			"Armor"
		]
	},

	"Abilities"       : "WQEQQRQWQWRWWEEREE",

	"Items"           : [
		{
			"Label"       : "Start",
			"Options"     : [
				"Hunter's Machete",
				"Refillable Potion",
				"Warding Totem"
			]
		},
		{
			"Label"       : "Pick 1",
			"Options"     : [
				"Skirmisher's Sabre (Warrior)",
				"Stalker's Blade (Warrior)"
			]
		},
		{
			"Label"       : "Pick 1",
			"Options"     : [
				"Ninja Tabi",
				"Mercury's Treads",
				"Boots of Mobility"
			]
		},
		{
			"Label"       : "Core",
			"Options"     : [
				"Black Cleaver",
				"Guardian Angel"
			]
		},
		{
			"Label"       : "Pick 2",
			"Options"     : [
				"Sterak's Gage",
				"Ravenous Hydra",
				"Titanic Hydra",
				"Dead Man's Plate",
				"Maw of Malmortius",
				"Edge of Night",
				"Youmuu's Ghostblade",
				"Duskblade of Draktharr"
			]
		},
		{
			"Label"       : "Consumables",
			"Options"     : [
				"Elixir of Wrath",
				"Control Ward"
			]
		}
	]
}
